{"src":"let angle = 0.5\n\ns.setup= ()=>{ \n  s.createCanvas(500, 500);\n  e.push(\"branch\")\n  e.push(\"left\")\n  console.log(e.val())\n  e.pop()\n  e.pop()\n} \n\ns.draw= ()=>{ \n  try{\n    \n  s.background(250);\n  s.translate(s.width/2, s.height);\n  e.push(\"branch\")\n    branch(100);\n  e.pop\n  }catch(e){\n    console.log(e)\n  }\n  \n}\n\nfunction branch(len) {\n  s.line(0, 0, 0, -len);\n  s.translate(0, -len);\n  if (len > 10) {\n    s.push();\n    e.push(\"right\")\n    s.rotate(angle+ (e.val()?? 0));\n    branch(len * 0.75)\n    e.pop();\n    s.pop();\n    \n    s.push();\n    e.push(\"left\");\n    \n    s.rotate(-angle+ (e.val()??0) );\n    branch(len * 0.75)\n\n    s.pop();  \n    e.pop();\n  }\n}","edit":{"branch":{"data":{"left":{"valueInfo":{"type":"number","value":-0.158,"max":1,"min":-1,"step":0.001},"data":{"left":{"valueInfo":{"type":"number","value":-0.179,"max":3,"min":-3,"step":0.001},"data":{"left":{"valueInfo":{"type":"number","value":-0.163,"max":2,"min":-2,"step":0.001}}}}}},"right":{"valueInfo":{"type":"number","value":0.172,"max":1,"min":-1,"step":0.001}}}}}}